azure/mgmt/regionmove/__init__.py
azure/mgmt/regionmove/_configuration.py
azure/mgmt/regionmove/_region_move_service_api.py
azure/mgmt/regionmove/_version.py
azure/mgmt/regionmove/aio/__init__.py
azure/mgmt/regionmove/aio/_configuration_async.py
azure/mgmt/regionmove/aio/_region_move_service_api_async.py
azure/mgmt/regionmove/aio/operations_async/__init__.py
azure/mgmt/regionmove/aio/operations_async/_move_collections_operations_async.py
azure/mgmt/regionmove/aio/operations_async/_move_resources_operations_async.py
azure/mgmt/regionmove/aio/operations_async/_operations_discovery_operations_async.py
azure/mgmt/regionmove/aio/operations_async/_unresolved_dependencies_operations_async.py
azure/mgmt/regionmove/models/__init__.py
azure/mgmt/regionmove/models/_models.py
azure/mgmt/regionmove/models/_models_py3.py
azure/mgmt/regionmove/models/_region_move_service_api_enums.py
azure/mgmt/regionmove/operations/__init__.py
azure/mgmt/regionmove/operations/_move_collections_operations.py
azure/mgmt/regionmove/operations/_move_resources_operations.py
azure/mgmt/regionmove/operations/_operations_discovery_operations.py
azure/mgmt/regionmove/operations/_unresolved_dependencies_operations.py
azure_mgmt_regionmove-1.0.0b1.dist-info/METADATA
azure_mgmt_regionmove-1.0.0b1.dist-info/WHEEL
azure_mgmt_regionmove-1.0.0b1.dist-info/top_level.txt
azure_mgmt_regionmove-1.0.0b1.dist-info/RECORD
